auro_utils/__init__.py
auro_utils/logger/__init__.py
auro_utils/logger/logger.py
auro_utils/logger/logger_classic.py
auro_utils/manager/__init__.py
auro_utils/manager/config_manager.py
auro_utils/manager/data_manager.py
auro_utils/manager/file_manager.py
auro_utils/math/__init__.py
auro_utils/math/transform.py
auro_utils/profiler/__init__.py
auro_utils/profiler/profiler.py
auro_utils-0.0.8.dist-info/licenses/LICENSE
auro_utils-0.0.8.dist-info/METADATA
auro_utils-0.0.8.dist-info/WHEEL
auro_utils-0.0.8.dist-info/top_level.txt
auro_utils-0.0.8.dist-info/RECORD
