Metadata-Version: 2.4
Name: auro_utils
Version: 0.0.8
Summary: Auro Utils is a utility package offering various practical supports for the Auromix application, such as enhanced logging capabilities and more.
Home-page: https://github.com/Hermanye996/auro_utils
Author: Herman Ye
Author-email: hermanye233@icloud.com
License: Apache Software License 2.0
Keywords: auro_utils
Classifier: Development Status :: 2 - Pre-Alpha
Classifier: Intended Audience :: Developers
Classifier: License :: OSI Approved :: Apache Software License
Classifier: Natural Language :: English
Classifier: Programming Language :: Python :: 3
Classifier: Programming Language :: Python :: 3.8
Requires-Python: >=3.8
License-File: LICENSE
Requires-Dist: colorlog
Requires-Dist: rospkg
Requires-Dist: loguru
Requires-Dist: toml
Requires-Dist: h5py
Requires-Dist: numpy
Requires-Dist: yappi
Requires-Dist: gprof2dot
Requires-Dist: pytest
Dynamic: author
Dynamic: author-email
Dynamic: classifier
Dynamic: description
Dynamic: description-content-type
Dynamic: home-page
Dynamic: keywords
Dynamic: license
Dynamic: license-file
Dynamic: requires-dist
Dynamic: requires-python
Dynamic: summary
